{
  "spaces": [
    {
      "slug": "bowies-boardroom",
      "parent_service_slug": "meeting-spaces",
      "status": "published",
      "name": "Bowie's Boardroom",
      "capacity_label": "4–12",
      "capacity_max": 12,
      "area_sqm": 40,
      "description_short": "boardroom style",
      "description_long": "Bowie's Boardroom is designed for focused work.",
      "sort_order": 1,
      "gallery_images": [
        {
          "image_ref": "/images/spaces/bowies-boardroom/gallery-01.jpg",
          "alt_text": "Bowie's Boardroom"
        },
        {
          "image_ref": "/images/spaces/bowies-boardroom/gallery-02.jpg",
          "alt_text": "Bowie's Boardroom"
        },
        {
          "image_ref": "/images/spaces/bowies-boardroom/gallery-03.jpg",
          "alt_text": "Bowie's Boardroom"
        },
        {
          "image_ref": "/images/spaces/bowies-boardroom/gallery-04.jpg",
          "alt_text": "Bowie's Boardroom"
        },
        {
          "image_ref": "/images/spaces/bowies-boardroom/gallery-05.jpg",
          "alt_text": "Bowie's Boardroom"
        },
        {
          "image_ref": "/images/spaces/bowies-boardroom/gallery-06.jpg",
          "alt_text": "Bowie's Boardroom"
        },
        {
          "image_ref": "/images/spaces/bowies-boardroom/gallery-07.jpg",
          "alt_text": "Bowie's Boardroom"
        },
        {
          "image_ref": "/images/spaces/bowies-boardroom/gallery-08.jpg",
          "alt_text": "Bowie's Boardroom"
        },
        {
          "image_ref": "/images/spaces/bowies-boardroom/gallery-09.jpg",
          "alt_text": "Bowie's Boardroom"
        }
      ]
    },
    {
      "slug": "amazons-meadow",
      "parent_service_slug": "meeting-spaces",
      "status": "published",
      "name": "Amazons' Meadow",
      "capacity_label": "13–40",
      "capacity_max": 40,
      "area_sqm": 70,
      "description_short": "adaptable layouts + private terrace",
      "description_long": "A spacious area perfect for workshops.",
      "sort_order": 2,
      "gallery_images": [
        {
          "image_ref": "/images/spaces/amazons-meadow/gallery-01.jpg",
          "alt_text": "Amazons' Meadow"
        },
        {
          "image_ref": "/images/spaces/amazons-meadow/gallery-02.jpg",
          "alt_text": "Amazons' Meadow"
        },
        {
          "image_ref": "/images/spaces/amazons-meadow/gallery-03.jpg",
          "alt_text": "Amazons' Meadow"
        },
        {
          "image_ref": "/images/spaces/amazons-meadow/gallery-04.jpg",
          "alt_text": "Amazons' Meadow"
        },
        {
          "image_ref": "/images/spaces/amazons-meadow/gallery-05.jpg",
          "alt_text": "Amazons' Meadow"
        },
        {
          "image_ref": "/images/spaces/amazons-meadow/gallery-06.jpg",
          "alt_text": "Amazons' Meadow"
        },
        {
          "image_ref": "/images/spaces/amazons-meadow/gallery-07.jpg",
          "alt_text": "Amazons' Meadow"
        },
        {
          "image_ref": "/images/spaces/amazons-meadow/gallery-08.jpg",
          "alt_text": "Amazons' Meadow"
        },
        {
          "image_ref": "/images/spaces/amazons-meadow/gallery-09.jpg",
          "alt_text": "Amazons' Meadow"
        },
        {
          "image_ref": "/images/spaces/amazons-meadow/gallery-010.jpg",
          "alt_text": "Amazons' Meadow"
        }
      ]
    },
    {
      "slug": "tokyos-lounge",
      "parent_service_slug": "meeting-spaces",
      "status": "published",
      "name": "Tokyo's Lounge",
      "capacity_label": "up to 20",
      "capacity_max": 20,
      "area_sqm": 45,
      "description_short": "flexible + terrace + fireplace",
      "description_long": "An informal setting with a fireplace.",
      "sort_order": 3,
      "gallery_images": [
        {
          "image_ref": "/images/spaces/tokyos-lounge/gallery-01.jpg",
          "alt_text": "Tokyo's Lounge"
        },
        {
          "image_ref": "/images/spaces/tokyos-lounge/gallery-02.jpg",
          "alt_text": "Tokyo's Lounge"
        },
        {
          "image_ref": "/images/spaces/tokyos-lounge/gallery-03.jpg",
          "alt_text": "Tokyo's Lounge"
        },
        {
          "image_ref": "/images/spaces/tokyos-lounge/gallery-04.jpg",
          "alt_text": "Tokyo's Lounge"
        },
        {
          "image_ref": "/images/spaces/tokyos-lounge/gallery-05.jpg",
          "alt_text": "Tokyo's Lounge"
        },
        {
          "image_ref": "/images/spaces/tokyos-lounge/gallery-06.jpg",
          "alt_text": "Tokyo's Lounge"
        },
        {
          "image_ref": "/images/spaces/tokyos-lounge/gallery-07.jpg",
          "alt_text": "Tokyo's Lounge"
        },
        {
          "image_ref": "/images/spaces/tokyos-lounge/gallery-08.jpg",
          "alt_text": "Tokyo's Lounge"
        },
        {
          "image_ref": "/images/spaces/tokyos-lounge/gallery-09.jpg",
          "alt_text": "Tokyo's Lounge"
        }
      ]
    }
  ]
}
